pfeature/Data/AAIndexNames.csv
pfeature/Data/Grantham.csv
pfeature/Data/PhysicoChemical.csv
pfeature/Data/Schneider-Wrede.csv
pfeature/Data/aa_attr_group.csv
pfeature/Data/aaind.txt
pfeature/Data/aaindex.csv
pfeature/Data/aaindices.csv
pfeature/Data/atom.csv
pfeature/Data/bin_di.csv
pfeature/Data/bonds.csv
pfeature/Data/can_pat.csv
pfeature/Data/data
pfeature/Data/z_aaindex.csv
pfeature/python_scripts/__init__.py
pfeature/python_scripts/pfeature_bin.py
pfeature/python_scripts/pfeature_comp.py
pfeature-1.4.dist-info/METADATA
pfeature-1.4.dist-info/WHEEL
pfeature-1.4.dist-info/entry_points.txt
pfeature-1.4.dist-info/top_level.txt
pfeature-1.4.dist-info/RECORD
