Metadata-Version: 2.1
Name: pfeature
Version: 1.4
Summary: A tool to compute the features of protein and peptide sequences
Home-page: https://github.com/raghavagps/pfeature
Requires-Python: >=3.6
Requires-Dist: numpy
Requires-Dist: pandas
